apistar_msgpack.py
apistar_msgpack-1.5.0.dist-info/DESCRIPTION.rst
apistar_msgpack-1.5.0.dist-info/METADATA
apistar_msgpack-1.5.0.dist-info/RECORD
apistar_msgpack-1.5.0.dist-info/WHEEL
apistar_msgpack-1.5.0.dist-info/metadata.json
apistar_msgpack-1.5.0.dist-info/top_level.txt
apistar_msgpack-1.5.0.dist-info/zip-safe
